COHDPS_Heatstryke/Main.py
COHDPS_Heatstryke/_init_.py
COHDPS_Heatstryke-0.1.0.dist-info/LICENSE
COHDPS_Heatstryke-0.1.0.dist-info/METADATA
COHDPS_Heatstryke-0.1.0.dist-info/WHEEL
COHDPS_Heatstryke-0.1.0.dist-info/top_level.txt
COHDPS_Heatstryke-0.1.0.dist-info/RECORD
